mappet/__init__.py
mappet/helpers.py
mappet/mappet.py
mappet-0.1.2.dist-info/DESCRIPTION.rst
mappet-0.1.2.dist-info/METADATA
mappet-0.1.2.dist-info/metadata.json
mappet-0.1.2.dist-info/pbr.json
mappet-0.1.2.dist-info/RECORD
mappet-0.1.2.dist-info/top_level.txt
mappet-0.1.2.dist-info/WHEEL
