Metadata-Version: 2.0
Name: mappet
Version: 0.1.2
Summary: Work with XML documents as if they were Python objects
Home-page: https://github.com/stxnext/mappet
Author: Radosław Szalski
Author-email: radoslaw.szalski@gmail.com
License: GNU Lesser General Public License v3(LGPLv3)
Keywords: xml parsing mapping
Platform: any
Classifier: Programming Language :: Python :: 2
Classifier: Programming Language :: Python :: 2.7
Classifier: Development Status :: 3 - Alpha
Classifier: Natural Language :: English
Classifier: Environment :: Web Environment
Classifier: Intended Audience :: Developers
Classifier: License :: OSI Approved :: GNU Lesser General Public License v3 (LGPLv3)
Classifier: Operating System :: OS Independent
Classifier: Topic :: Software Development :: Libraries :: Python Modules
Classifier: Topic :: Text Processing :: Markup :: XML
Classifier: Topic :: Utilities
Requires-Dist: lxml
Requires-Dist: python-dateutil
Provides-Extra: testing
Requires-Dist: pytest; extra == 'testing'
Requires-Dist: mock; extra == 'testing'
Requires-Dist: tox; extra == 'testing'
